{
  "minecraft:recipes/tools/fishing_rod": {
    "criteria": {
      "has_string": "2025-10-16 04:06:01 +0000"
    },
    "done": true
  },
  "securitycraft:recipes/securitycraft/universal_block_remover": {
    "criteria": {
      "has_iron": "2025-10-16 04:09:55 +0000"
    },
    "done": true
  },
  "scalinghealth:recipes/scalinghealth/power_crystal": {
    "criteria": {
      "cobblestone": "2025-10-16 03:50:15 +0000"
    },
    "done": true
  },
  "minecraft:recipes/redstone/lever": {
    "criteria": {
      "has_cobblestone": "2025-10-16 03:50:15 +0000"
    },
    "done": true
  },
  "minecraft:recipes/building_blocks/cobblestone_stairs_from_cobblestone_stonecutting": {
    "criteria": {
      "has_cobblestone": "2025-10-16 03:50:15 +0000"
    },
    "done": true
  },
  "farmersdelight:recipes/farmersdelight/organic_compost_from_rotten_flesh": {
    "criteria": {
      "has_rotten_flesh": "2025-10-16 04:05:36 +0000"
    },
    "done": true
  },
  "minecraft:recipes/combat/iron_sword": {
    "criteria": {
      "has_iron_ingot": "2025-10-16 04:09:55 +0000"
    },
    "done": true
  },
  "morevillagers:first_village": {
    "criteria": {
      "village": "2025-10-16 05:46:49 +0000"
    },
    "done": true
  },
  "securitycraft:recipes/securitycraft/reinforced_andesite_with_vanilla_diorite": {
    "criteria": {
      "has_cobblestone": "2025-10-16 03:50:15 +0000"
    },
    "done": true
  },
  "minecraft:recipes/redstone/spruce_door": {
    "criteria": {
      "has_planks": "2025-10-16 04:47:13 +0000"
    },
    "done": true
  },
  "minecraft:recipes/misc/wheat": {
    "criteria": {
      "has_hay_block": "2025-10-16 03:53:09 +0000"
    },
    "done": true
  },
  "biomesoplenty:recipes/transportation/willow_boat": {
    "criteria": {
      "in_water": "2025-10-16 03:52:13 +0000"
    },
    "done": true
  },
  "securitycraft:recipes/securitycraft/reinforced_spruce_fence": {
    "criteria": {
      "has_stick": "2025-10-16 03:49:59 +0000"
    },
    "done": true
  },
  "securitycraft:recipes/securitycraft/sentry": {
    "criteria": {
      "has_iron": "2025-10-16 04:09:55 +0000"
    },
    "done": true
  },
  "betterendforge:recipes/betterendforge/iron_chandelier": {
    "criteria": {
      "has_iron_ingot": "2025-10-16 04:09:55 +0000"
    },
    "done": true
  },
  "scalinghealth:recipes/scalinghealth/medkit": {
    "criteria": {
      "cobblestone": "2025-10-16 03:50:15 +0000"
    },
    "done": true
  },
  "minecraft:recipes/building_blocks/chiseled_stone_bricks": {
    "criteria": {
      "has_stone_bricks": "2025-10-16 04:09:55 +0000"
    },
    "done": true
  },
  "minecraft:recipes/tools/iron_pickaxe": {
    "criteria": {
      "has_iron_ingot": "2025-10-16 04:09:55 +0000"
    },
    "done": true
  },
  "minecraft:recipes/building_blocks/stone_brick_slab_from_stone_bricks_stonecutting": {
    "criteria": {
      "has_stone_bricks": "2025-10-16 04:09:55 +0000"
    },
    "done": true
  },
  "minecraft:recipes/redstone/spruce_fence_gate": {
    "criteria": {
      "has_planks": "2025-10-16 04:47:13 +0000"
    },
    "done": true
  },
  "minecraft:recipes/combat/leather_helmet": {
    "criteria": {
      "has_leather": "2025-10-16 03:52:04 +0000"
    },
    "done": true
  },
  "minecraft:recipes/redstone/birch_pressure_plate": {
    "criteria": {
      "has_planks": "2025-10-16 05:46:58 +0000"
    },
    "done": true
  },
  "minecraft:recipes/decorations/crafting_table": {
    "criteria": {
      "has_planks": "2025-10-16 03:49:57 +0000"
    },
    "done": true
  },
  "minecraft:recipes/decorations/campfire": {
    "criteria": {
      "has_stick": "2025-10-16 03:49:59 +0000"
    },
    "done": true
  },
  "minecraft:recipes/tools/golden_hoe": {
    "criteria": {
      "has_gold_ingot": "2025-10-16 05:51:43 +0000"
    },
    "done": true
  },
  "minecraft:recipes/misc/melon_seeds": {
    "criteria": {
      "has_melon": "2025-10-16 04:04:54 +0000"
    },
    "done": true
  },
  "biomesoplenty:recipes/transportation/mahogany_boat": {
    "criteria": {
      "in_water": "2025-10-16 03:52:13 +0000"
    },
    "done": true
  },
  "iceandfire:iceandfire/root": {
    "criteria": {
      "tick": "2025-10-16 03:48:32 +0000"
    },
    "done": true
  },
  "minecraft:recipes/decorations/ladder": {
    "criteria": {
      "has_stick": "2025-10-16 03:49:59 +0000"
    },
    "done": true
  },
  "conjurer_illager:find_theatre": {
    "criteria": {
      "in_city": "2025-10-16 04:34:35 +0000"
    },
    "done": true
  },
  "minecraft:recipes/building_blocks/dark_oak_slab": {
    "criteria": {
      "has_planks": "2025-10-16 04:06:01 +0000"
    },
    "done": true
  },
  "minecraft:recipes/misc/iron_nugget": {
    "criteria": {
      "has_iron_ingot": "2025-10-16 04:09:55 +0000"
    },
    "done": true
  },
  "minecraft:recipes/decorations/chest": {
    "criteria": {
      "has_lots_of_items": "2025-10-16 03:52:04 +0000"
    },
    "done": true
  },
  "blue_skies:recipes/blue_skies_everdawn_blocks/maple_stairs": {
    "criteria": {
      "has_item": "2025-10-16 04:01:41 +0000"
    },
    "done": true
  },
  "minecraft:recipes/combat/golden_sword": {
    "criteria": {
      "has_gold_ingot": "2025-10-16 05:51:43 +0000"
    },
    "done": true
  },
  "minecraft:recipes/redstone/spruce_button": {
    "criteria": {
      "has_planks": "2025-10-16 04:47:13 +0000"
    },
    "done": true
  },
  "minecraft:recipes/tools/wooden_shovel": {
    "criteria": {
      "has_stick": "2025-10-16 03:49:59 +0000"
    },
    "done": true
  },
  "securitycraft:recipes/securitycraft/track_mine": {
    "criteria": {
      "has_iron": "2025-10-16 04:09:55 +0000"
    },
    "done": true
  },
  "minecraft:recipes/decorations/torch": {
    "criteria": {
      "has_stone_pickaxe": "2025-10-16 03:51:18 +0000"
    },
    "done": true
  },
  "aquaculture:recipes/tools/golden_fishing_rod": {
    "criteria": {
      "has_gold": "2025-10-16 05:51:43 +0000"
    },
    "done": true
  },
  "betterendforge:recipes/betterendforge/thallasium_pickaxe_smithing": {
    "criteria": {
      "has_stick": "2025-10-16 03:49:59 +0000"
    },
    "done": true
  },
  "minecraft:recipes/redstone/dark_oak_button": {
    "criteria": {
      "has_planks": "2025-10-16 04:06:01 +0000"
    },
    "done": true
  },
  "biomesoplenty:recipes/transportation/dead_boat": {
    "criteria": {
      "in_water": "2025-10-16 03:52:13 +0000"
    },
    "done": true
  },
  "minecraft:recipes/tools/shears": {
    "criteria": {
      "has_iron_ingot": "2025-10-16 04:09:55 +0000"
    },
    "done": true
  },
  "minecraft:recipes/misc/stick": {
    "criteria": {
      "has_planks": "2025-10-16 03:49:57 +0000"
    },
    "done": true
  },
  "betterendforge:recipes/betterendforge/terminite_hammer_smithing": {
    "criteria": {
      "has_stick": "2025-10-16 03:49:59 +0000"
    },
    "done": true
  },
  "blue_skies:recipes/blue_skies_tools/maple_axe": {
    "criteria": {
      "has_resource": "2025-10-16 04:01:41 +0000"
    },
    "done": true
  },
  "blue_skies:recipes/blue_skies_everdawn_blocks/maple_fence": {
    "criteria": {
      "has_item": "2025-10-16 04:01:41 +0000"
    },
    "done": true
  },
  "betterendforge:recipes/betterendforge/iron_hammer": {
    "criteria": {
      "has_iron_ingot": "2025-10-16 04:09:55 +0000"
    },
    "done": true
  },
  "securitycraft:recipes/securitycraft/reinforced_oak_fence": {
    "criteria": {
      "has_stick": "2025-10-16 03:49:59 +0000"
    },
    "done": true
  },
  "minecraft:recipes/transportation/spruce_boat": {
    "criteria": {
      "in_water": "2025-10-16 03:52:13 +0000"
    },
    "done": true
  },
  "aquaculture:recipes/tools/wooden_fillet_knife": {
    "criteria": {
      "has_items": "2025-10-16 03:49:59 +0000"
    },
    "done": true
  },
  "minecraft:recipes/building_blocks/cracked_stone_bricks": {
    "criteria": {
      "has_stone_bricks": "2025-10-16 04:09:55 +0000"
    },
    "done": true
  },
  "securitycraft:recipes/securitycraft/blacklist_module": {
    "criteria": {
      "has_iron": "2025-10-16 04:09:55 +0000"
    },
    "done": true
  },
  "securitycraft:recipes/securitycraft/speed_module": {
    "criteria": {
      "has_iron": "2025-10-16 04:09:55 +0000"
    },
    "done": true
  },
  "minecraft:recipes/redstone/dispenser": {
    "criteria": {
      "has_bow": "2025-10-16 04:47:18 +0000"
    },
    "done": true
  },
  "farmersdelight:recipes/farmersdelight/skillet": {
    "criteria": {
      "has_brick": "2025-10-16 04:04:54 +0000"
    },
    "done": true
  },
  "securitycraft:recipes/securitycraft/electrified_iron_fence": {
    "criteria": {
      "has_iron": "2025-10-16 04:09:55 +0000"
    },
    "done": true
  },
  "securitycraft:recipes/securitycraft/harming_module": {
    "criteria": {
      "has_iron": "2025-10-16 04:09:55 +0000"
    },
    "done": true
  },
  "minecraft:recipes/building_blocks/emerald_block": {
    "criteria": {
      "has_emerald": "2025-10-16 04:24:12 +0000"
    },
    "done": true
  },
  "minecraft:recipes/building_blocks/dark_oak_planks": {
    "criteria": {
      "has_log": "2025-10-16 04:15:05 +0000"
    },
    "done": true
  },
  "securitycraft:recipes/securitycraft/reinforced_dark_oak_fence_gate": {
    "criteria": {
      "has_stick": "2025-10-16 03:49:59 +0000"
    },
    "done": true
  },
  "securitycraft:recipes/securitycraft/reinforced_andesite_with_vanilla_cobblestone": {
    "criteria": {
      "has_cobblestone": "2025-10-16 03:50:15 +0000"
    },
    "done": true
  },
  "minecraft:recipes/misc/sugar_from_sugar_cane": {
    "criteria": {
      "has_reeds": "2025-10-16 04:06:21 +0000"
    },
    "done": true
  },
  "minecraft:recipes/misc/gold_nugget": {
    "criteria": {
      "has_gold_ingot": "2025-10-16 05:51:43 +0000"
    },
    "done": true
  },
  "tombstone:adventure/find_grave_dust": {
    "criteria": {
      "from_undead": "2025-10-16 03:55:40 +0000"
    },
    "done": true
  },
  "minecraft:recipes/combat/iron_leggings": {
    "criteria": {
      "has_iron_ingot": "2025-10-16 04:09:55 +0000"
    },
    "done": true
  },
  "farmersdelight:recipes/farmersdelight/steak_and_potatoes": {
    "criteria": {
      "has_baked_potato": "2025-10-16 04:16:05 +0000"
    },
    "done": true
  },
  "minecraft:recipes/redstone/dark_oak_door": {
    "criteria": {
      "has_planks": "2025-10-16 04:06:01 +0000"
    },
    "done": true
  },
  "minecraft:husbandry/balanced_diet": {
    "criteria": {
      "cooked_beef": "2025-10-16 04:05:20 +0000",
      "baked_potato": "2025-10-16 04:21:19 +0000",
      "apple": "2025-10-16 04:12:44 +0000",
      "golden_apple": "2025-10-16 04:44:35 +0000",
      "carrot": "2025-10-16 04:13:11 +0000"
    },
    "done": false
  },
  "minecraft:recipes/tools/wooden_hoe": {
    "criteria": {
      "has_stick": "2025-10-16 03:49:59 +0000"
    },
    "done": true
  },
  "tombstone:recipes/from_grave_key": {
    "criteria": {
      "has_ingredient": "2025-10-16 03:56:55 +0000"
    },
    "done": true
  },
  "minecraft:recipes/brewing/golden_carrot": {
    "criteria": {
      "has_gold_nugget": "2025-10-16 04:47:19 +0000"
    },
    "done": true
  },
  "blue_skies:recipes/blue_skies_tools/maple_pickaxe": {
    "criteria": {
      "has_resource": "2025-10-16 04:01:41 +0000"
    },
    "done": true
  },
  "minecraft:recipes/combat/shield": {
    "criteria": {
      "has_iron_ingot": "2025-10-16 04:09:55 +0000"
    },
    "done": true
  },
  "minecraft:recipes/building_blocks/cobblestone_slab": {
    "criteria": {
      "has_cobblestone": "2025-10-16 03:50:15 +0000"
    },
    "done": true
  },
  "minecraft:recipes/misc/bucket": {
    "criteria": {
      "has_iron_ingot": "2025-10-16 04:09:55 +0000"
    },
    "done": true
  },
  "minecraft:recipes/redstone/trapped_chest": {
    "criteria": {
      "has_tripwire_hook": "2025-10-16 04:44:19 +0000"
    },
    "done": true
  },
  "minecraft:recipes/building_blocks/cobblestone_stairs": {
    "criteria": {
      "has_cobblestone": "2025-10-16 03:50:15 +0000"
    },
    "done": true
  },
  "minecraft:recipes/redstone/hopper": {
    "criteria": {
      "has_iron_ingot": "2025-10-16 04:09:55 +0000"
    },
    "done": true
  },
  "minecraft:recipes/building_blocks/stone_brick_stairs_from_stone_bricks_stonecutting": {
    "criteria": {
      "has_stone_bricks": "2025-10-16 04:09:55 +0000"
    },
    "done": true
  },
  "aquaculture:recipes/tools/gold_fillet_knife": {
    "criteria": {
      "has_items": "2025-10-16 05:51:43 +0000"
    },
    "done": true
  },
  "biomesoplenty:recipes/transportation/magic_boat": {
    "criteria": {
      "in_water": "2025-10-16 03:52:13 +0000"
    },
    "done": true
  },
  "minecraft:recipes/building_blocks/birch_slab": {
    "criteria": {
      "has_planks": "2025-10-16 05:46:58 +0000"
    },
    "done": true
  },
  "mutantbeasts:root": {
    "criteria": {
      "killed_something": "2025-10-16 03:52:03 +0000"
    },
    "done": true
  },
  "tombstone:adventure/first_grave": {
    "criteria": {
      "coded_trigger": "2025-10-16 03:56:53 +0000"
    },
    "done": true
  },
  "securitycraft:recipes/securitycraft/redstone_module": {
    "criteria": {
      "has_iron": "2025-10-16 04:09:55 +0000"
    },
    "done": true
  },
  "securitycraft:recipes/securitycraft/reinforced_spruce_fence_gate": {
    "criteria": {
      "has_stick": "2025-10-16 03:49:59 +0000"
    },
    "done": true
  },
  "biomesoplenty:recipes/transportation/cherry_boat": {
    "criteria": {
      "in_water": "2025-10-16 03:52:13 +0000"
    },
    "done": true
  },
  "vanillaexcavators:recipes/tools/wood_excavator": {
    "criteria": {
      "has_material": "2025-10-16 03:49:30 +0000"
    },
    "done": true
  },
  "biomesoplenty:recipes/transportation/fir_boat": {
    "criteria": {
      "in_water": "2025-10-16 03:52:13 +0000"
    },
    "done": true
  },
  "minecraft:recipes/misc/leather_horse_armor": {
    "criteria": {
      "has_leather": "2025-10-16 03:52:04 +0000"
    },
    "done": true
  },
  "minecraft:recipes/combat/leather_leggings": {
    "criteria": {
      "has_leather": "2025-10-16 03:52:04 +0000"
    },
    "done": true
  },
  "mutantmore:mutantmore/root": {
    "criteria": {
      "crafting_table": "2025-10-16 03:49:59 +0000"
    },
    "done": true
  },
  "minecraft:recipes/combat/iron_helmet": {
    "criteria": {
      "has_iron_ingot": "2025-10-16 04:09:55 +0000"
    },
    "done": true
  },
  "minecraft:recipes/tools/golden_shovel": {
    "criteria": {
      "has_gold_ingot": "2025-10-16 05:51:43 +0000"
    },
    "done": true
  },
  "minecraft:recipes/combat/bow": {
    "criteria": {
      "has_string": "2025-10-16 04:06:01 +0000"
    },
    "done": true
  },
  "securitycraft:recipes/securitycraft/security_camera": {
    "criteria": {
      "has_iron": "2025-10-16 04:09:55 +0000"
    },
    "done": true
  },
  "minecraft:recipes/redstone/oak_fence_gate": {
    "criteria": {
      "has_planks": "2025-10-16 03:49:57 +0000"
    },
    "done": true
  },
  "securitycraft:recipes/securitycraft/door_indestructible_iron_item": {
    "criteria": {
      "has_iron": "2025-10-16 04:09:55 +0000"
    },
    "done": true
  },
  "minecraft:recipes/decorations/iron_bars": {
    "criteria": {
      "has_iron_ingot": "2025-10-16 04:09:55 +0000"
    },
    "done": true
  },
  "takesapillage:root": {
    "criteria": {
      "always": "2025-10-16 03:48:32 +0000"
    },
    "done": true
  },
  "betterendforge:recipes/betterendforge/thallasium_sword_handle_smithing": {
    "criteria": {
      "has_stick": "2025-10-16 03:49:59 +0000"
    },
    "done": true
  },
  "securitycraft:recipes/securitycraft/reinforced_crimson_fence_gate": {
    "criteria": {
      "has_stick": "2025-10-16 03:49:59 +0000"
    },
    "done": true
  },
  "minecraft:recipes/building_blocks/gold_block": {
    "criteria": {
      "has_gold_ingot": "2025-10-16 05:51:43 +0000"
    },
    "done": true
  },
  "securitycraft:recipes/securitycraft/reinforced_birch_fence_gate": {
    "criteria": {
      "has_stick": "2025-10-16 03:49:59 +0000"
    },
    "done": true
  },
  "minecraft:story/obtain_armor": {
    "criteria": {
      "iron_boots": "2025-10-16 04:42:50 +0000"
    },
    "done": true
  },
  "betterendforge:recipes/betterendforge/terminite_pickaxe_smithing": {
    "criteria": {
      "has_stick": "2025-10-16 03:49:59 +0000"
    },
    "done": true
  },
  "minecraft:story/mine_stone": {
    "criteria": {
      "get_stone": "2025-10-16 03:50:15 +0000"
    },
    "done": true
  },
  "minecraft:recipes/redstone/target": {
    "criteria": {
      "has_hay_block": "2025-10-16 03:53:09 +0000"
    },
    "done": true
  },
  "minecraft:recipes/decorations/furnace": {
    "criteria": {
      "has_cobblestone": "2025-10-16 03:50:15 +0000"
    },
    "done": true
  },
  "minecraft:recipes/transportation/minecart": {
    "criteria": {
      "has_iron_ingot": "2025-10-16 04:09:55 +0000"
    },
    "done": true
  },
  "securitycraft:recipes/securitycraft/reinforced_acacia_fence_gate": {
    "criteria": {
      "has_stick": "2025-10-16 03:49:59 +0000"
    },
    "done": true
  },
  "betterendforge:recipes/betterendforge/leather_to_stripes": {
    "criteria": {
      "has_leather": "2025-10-16 03:52:04 +0000"
    },
    "done": true
  },
  "morevillagers:root": {
    "criteria": {
      "always": "2025-10-16 03:48:32 +0000"
    },
    "done": true
  },
  "minecraft:recipes/brewing/cauldron": {
    "criteria": {
      "has_water_bucket": "2025-10-16 05:47:15 +0000"
    },
    "done": true
  },
  "securitycraft:recipes/securitycraft/reinforced_jungle_fence": {
    "criteria": {
      "has_stick": "2025-10-16 03:49:59 +0000"
    },
    "done": true
  },
  "minecraft:recipes/misc/charcoal": {
    "criteria": {
      "has_log": "2025-10-16 03:49:30 +0000"
    },
    "done": true
  },
  "minecraft:recipes/tools/wooden_pickaxe": {
    "criteria": {
      "has_stick": "2025-10-16 03:49:59 +0000"
    },
    "done": true
  },
  "minecraft:recipes/tools/iron_hoe": {
    "criteria": {
      "has_iron_ingot": "2025-10-16 04:09:55 +0000"
    },
    "done": true
  },
  "minecraft:recipes/building_blocks/cobblestone_slab_from_cobblestone_stonecutting": {
    "criteria": {
      "has_cobblestone": "2025-10-16 03:50:15 +0000"
    },
    "done": true
  },
  "minecraft:husbandry/root": {
    "criteria": {
      "consumed_item": "2025-10-16 03:49:32 +0000"
    },
    "done": true
  },
  "minecraft:recipes/building_blocks/stone_brick_slab": {
    "criteria": {
      "has_stone_bricks": "2025-10-16 04:09:55 +0000"
    },
    "done": true
  },
  "shieldexp:recipes/iron_shield": {
    "criteria": {
      "has_iron_ingot": "2025-10-16 03:48:31 +0000"
    },
    "done": true
  },
  "minecraft:recipes/transportation/birch_boat": {
    "criteria": {
      "in_water": "2025-10-16 03:52:13 +0000"
    },
    "done": true
  },
  "minecraft:recipes/food/golden_apple": {
    "criteria": {
      "has_gold_ingot": "2025-10-16 05:51:43 +0000"
    },
    "done": true
  },
  "tombstone:adventure/eat_easter_egg_food": {
    "criteria": {
      "coded_trigger": "2025-10-16 03:49:32 +0000"
    },
    "done": true
  },
  "blue_skies:recipes/blue_skies_tools/maple_shovel": {
    "criteria": {
      "has_resource": "2025-10-16 04:01:41 +0000"
    },
    "done": true
  },
  "minecraft:recipes/building_blocks/oak_stairs": {
    "criteria": {
      "has_planks": "2025-10-16 03:49:57 +0000"
    },
    "done": true
  },
  "securitycraft:recipes/securitycraft/sonic_security_system": {
    "criteria": {
      "has_stick": "2025-10-16 03:49:59 +0000"
    },
    "done": true
  },
  "farmersdelight:recipes/farmersdelight/roasted_mutton_chops": {
    "criteria": {
      "has_mutton": "2025-10-16 04:04:54 +0000"
    },
    "done": true
  },
  "minecraft:recipes/transportation/acacia_boat": {
    "criteria": {
      "in_water": "2025-10-16 03:52:13 +0000"
    },
    "done": true
  },
  "minecraft:recipes/tools/iron_shovel": {
    "criteria": {
      "has_iron_ingot": "2025-10-16 04:09:55 +0000"
    },
    "done": true
  },
  "conjurer_illager:kill_conjurer": {
    "criteria": {
      "kill_conjurer": "2025-10-16 04:45:09 +0000"
    },
    "done": true
  },
  "minecraft:recipes/redstone/iron_trapdoor": {
    "criteria": {
      "has_iron_ingot": "2025-10-16 04:09:55 +0000"
    },
    "done": true
  },
  "minecraft:recipes/building_blocks/dark_oak_wood": {
    "criteria": {
      "has_log": "2025-10-16 04:15:05 +0000"
    },
    "done": true
  },
  "aquaculture:recipes/tools/iron_fillet_knife": {
    "criteria": {
      "has_items": "2025-10-16 04:09:55 +0000"
    },
    "done": true
  },
  "blue_skies:recipes/blue_skies_everdawn_blocks/maple_button": {
    "criteria": {
      "has_item": "2025-10-16 04:01:41 +0000"
    },
    "done": true
  },
  "aquaculture:recipes/tools/iron_fishing_rod": {
    "criteria": {
      "has_iron": "2025-10-16 04:09:55 +0000"
    },
    "done": true
  },
  "farmersdelight:recipes/farmersdelight/cutting_board": {
    "criteria": {
      "has_stick": "2025-10-16 03:49:59 +0000"
    },
    "done": true
  },
  "minecraft:recipes/decorations/birch_sign": {
    "criteria": {
      "has_birch_planks": "2025-10-16 05:46:58 +0000"
    },
    "done": true
  },
  "aquaculture:recipes/tools/stone_fillet_knife": {
    "criteria": {
      "has_items": "2025-10-16 03:50:15 +0000"
    },
    "done": true
  },
  "minecraft:adventure/root": {
    "criteria": {
      "killed_something": "2025-10-16 03:52:03 +0000"
    },
    "done": true
  },
  "securitycraft:recipes/securitycraft/storage_module": {
    "criteria": {
      "has_iron": "2025-10-16 04:09:55 +0000"
    },
    "done": true
  },
  "farmersdelight:main/root": {
    "criteria": {
      "seeds": "2025-10-16 03:48:31 +0000"
    },
    "done": true
  },
  "minecraft:recipes/decorations/item_frame": {
    "criteria": {
      "has_leather": "2025-10-16 03:52:04 +0000"
    },
    "done": true
  },
  "farmersdelight:recipes/farmersdelight/chicken_sandwich": {
    "criteria": {
      "has_cooked_chicken": "2025-10-16 04:04:54 +0000"
    },
    "done": true
  },
  "shieldexp:recipes/wooden_shield": {
    "criteria": {
      "has_stick": "2025-10-16 03:48:31 +0000"
    },
    "done": true
  },
  "minecraft:recipes/tools/stone_hoe": {
    "criteria": {
      "has_cobblestone": "2025-10-16 03:50:15 +0000"
    },
    "done": true
  },
  "minecraft:recipes/building_blocks/white_wool_from_string": {
    "criteria": {
      "has_string": "2025-10-16 04:06:01 +0000"
    },
    "done": true
  },
  "minecraft:recipes/decorations/spruce_fence": {
    "criteria": {
      "has_planks": "2025-10-16 04:47:13 +0000"
    },
    "done": true
  },
  "farmersdelight:recipes/farmersdelight/melon_popsicle": {
    "criteria": {
      "has_melon": "2025-10-16 04:04:54 +0000"
    },
    "done": true
  },
  "minecraft:adventure/kill_all_mobs": {
    "criteria": {
      "minecraft:skeleton": "2025-10-16 03:54:59 +0000",
      "minecraft:spider": "2025-10-16 03:56:20 +0000",
      "minecraft:creeper": "2025-10-16 05:35:49 +0000",
      "minecraft:zombie": "2025-10-16 03:55:40 +0000",
      "minecraft:zombie_villager": "2025-10-16 04:09:28 +0000"
    },
    "done": false
  },
  "minecraft:recipes/building_blocks/dark_oak_stairs": {
    "criteria": {
      "has_planks": "2025-10-16 04:06:01 +0000"
    },
    "done": true
  },
  "farmersdelight:recipes/farmersdelight/cooking_pot": {
    "criteria": {
      "has_iron_ingot": "2025-10-16 04:09:55 +0000"
    },
    "done": true
  },
  "minecraft:recipes/food/cooked_beef_from_smoking": {
    "criteria": {
      "has_beef": "2025-10-16 03:52:04 +0000"
    },
    "done": true
  },
  "minecraft:recipes/decorations/stone_brick_wall": {
    "criteria": {
      "has_stone_bricks": "2025-10-16 04:09:55 +0000"
    },
    "done": true
  },
  "minecraft:recipes/brewing/glistering_melon_slice": {
    "criteria": {
      "has_melon": "2025-10-16 04:04:54 +0000"
    },
    "done": true
  },
  "minecraft:recipes/decorations/dark_oak_sign": {
    "criteria": {
      "has_dark_oak_planks": "2025-10-16 04:06:01 +0000"
    },
    "done": true
  },
  "minecraft:recipes/building_blocks/spruce_stairs": {
    "criteria": {
      "has_planks": "2025-10-16 04:47:13 +0000"
    },
    "done": true
  },
  "dungeons_arise:find_merchant_campsite": {
    "criteria": {
      "location0": "2025-10-16 05:30:53 +0000"
    },
    "done": true
  },
  "minecraft:recipes/redstone/dark_oak_fence_gate": {
    "criteria": {
      "has_planks": "2025-10-16 04:06:01 +0000"
    },
    "done": true
  },
  "minecraft:recipes/misc/iron_nugget_from_smelting": {
    "criteria": {
      "has_chainmail_chestplate": "2025-10-16 04:04:31 +0000"
    },
    "done": true
  },
  "blue_skies:recipes/blue_skies_tools/maple_sword": {
    "criteria": {
      "has_resource": "2025-10-16 04:01:41 +0000"
    },
    "done": true
  },
  "minecraft:recipes/redstone/birch_door": {
    "criteria": {
      "has_planks": "2025-10-16 05:46:58 +0000"
    },
    "done": true
  },
  "morevillagers:all_workstations_get": {
    "criteria": {
      "barrel": "2025-10-16 03:53:16 +0000"
    },
    "done": false
  },
  "minecraft:recipes/decorations/chain": {
    "criteria": {
      "has_iron_ingot": "2025-10-16 04:09:55 +0000"
    },
    "done": true
  },
  "minecraft:recipes/misc/gold_ingot_from_nuggets": {
    "criteria": {
      "has_gold_nugget": "2025-10-16 04:47:19 +0000"
    },
    "done": true
  },
  "tombstone:adventure/first_knowledge": {
    "criteria": {
      "coded_trigger": "2025-10-16 03:49:32 +0000"
    },
    "done": true
  },
  "securitycraft:recipes/securitycraft/reinforced_warped_fence_gate": {
    "criteria": {
      "has_stick": "2025-10-16 03:49:59 +0000"
    },
    "done": true
  },
  "minecraft:story/upgrade_tools": {
    "criteria": {
      "stone_pickaxe": "2025-10-16 03:51:18 +0000"
    },
    "done": true
  },
  "securitycraft:recipes/securitycraft/reinforced_dispenser": {
    "criteria": {
      "has_bow": "2025-10-16 04:47:18 +0000"
    },
    "done": true
  },
  "alexsmobs:alexsmobs/root": {
    "criteria": {
      "useitem": "2025-10-16 03:49:32 +0000"
    },
    "done": true
  },
  "minecraft:recipes/decorations/oak_fence": {
    "criteria": {
      "has_planks": "2025-10-16 03:49:57 +0000"
    },
    "done": true
  },
  "minecraft:recipes/transportation/oak_boat": {
    "criteria": {
      "in_water": "2025-10-16 03:52:13 +0000"
    },
    "done": true
  },
  "minecraft:recipes/decorations/birch_fence": {
    "criteria": {
      "has_planks": "2025-10-16 05:46:58 +0000"
    },
    "done": true
  },
  "betterendforge:recipes/betterendforge/terminite_sword_handle_smithing": {
    "criteria": {
      "has_stick": "2025-10-16 03:49:59 +0000"
    },
    "done": true
  },
  "betterendforge:recipes/betterendforge/gold_chandelier": {
    "criteria": {
      "has_gold_ingot": "2025-10-16 05:51:43 +0000"
    },
    "done": true
  },
  "minecraft:recipes/building_blocks/oak_slab": {
    "criteria": {
      "has_planks": "2025-10-16 03:49:57 +0000"
    },
    "done": true
  },
  "minecraft:recipes/building_blocks/stone_brick_stairs": {
    "criteria": {
      "has_stone_bricks": "2025-10-16 04:09:55 +0000"
    },
    "done": true
  },
  "betterendforge:recipes/betterendforge/thallasium_hammer_smithing": {
    "criteria": {
      "has_stick": "2025-10-16 03:49:59 +0000"
    },
    "done": true
  },
  "minecraft:recipes/combat/golden_boots": {
    "criteria": {
      "has_gold_ingot": "2025-10-16 05:51:43 +0000"
    },
    "done": true
  },
  "securitycraft:recipes/securitycraft/reinforced_crimson_fence": {
    "criteria": {
      "has_stick": "2025-10-16 03:49:59 +0000"
    },
    "done": true
  },
  "farmersdelight:recipes/farmersdelight/roast_chicken_block": {
    "criteria": {
      "has_cooked_chicken": "2025-10-16 04:04:54 +0000"
    },
    "done": true
  },
  "upgradednetherite_items:recipes/upgraded_netherite_pearl_smithing": {
    "criteria": {
      "has_ender_pearl": "2025-10-16 04:19:52 +0000"
    },
    "done": true
  },
  "minecraft:recipes/tools/wooden_axe": {
    "criteria": {
      "has_stick": "2025-10-16 03:49:59 +0000"
    },
    "done": true
  },
  "minecraft:recipes/decorations/spruce_sign": {
    "criteria": {
      "has_spruce_planks": "2025-10-16 04:47:13 +0000"
    },
    "done": true
  },
  "betterendforge:recipes/betterendforge/golden_hammer": {
    "criteria": {
      "has_gold_ingot": "2025-10-16 05:51:43 +0000"
    },
    "done": true
  },
  "securitycraft:recipes/securitycraft/keycard_lv2": {
    "criteria": {
      "has_iron": "2025-10-16 04:09:55 +0000"
    },
    "done": true
  },
  "betterendforge:recipes/betterendforge/thallasium_shovel_smithing": {
    "criteria": {
      "has_stick": "2025-10-16 03:49:59 +0000"
    },
    "done": true
  },
  "securitycraft:recipes/securitycraft/keycard_lv1": {
    "criteria": {
      "has_iron": "2025-10-16 04:09:55 +0000"
    },
    "done": true
  },
  "minecraft:recipes/misc/paper": {
    "criteria": {
      "has_reeds": "2025-10-16 04:06:21 +0000"
    },
    "done": true
  },
  "shieldexp:recipes/diamond_shield": {
    "criteria": {
      "has_diamond": "2025-10-16 03:48:31 +0000"
    },
    "done": true
  },
  "tombstone:adventure/ashes_and_bones": {
    "criteria": {
      "coded_trigger": "2025-10-16 04:20:38 +0000"
    },
    "done": true
  },
  "minecraft:recipes/combat/golden_chestplate": {
    "criteria": {
      "has_gold_ingot": "2025-10-16 05:51:43 +0000"
    },
    "done": true
  },
  "biomesoplenty:recipes/transportation/umbran_boat": {
    "criteria": {
      "in_water": "2025-10-16 03:52:13 +0000"
    },
    "done": true
  },
  "minecraft:recipes/decorations/loom": {
    "criteria": {
      "has_string": "2025-10-16 04:06:01 +0000"
    },
    "done": true
  },
  "biomesoplenty:recipes/transportation/palm_boat": {
    "criteria": {
      "in_water": "2025-10-16 03:52:13 +0000"
    },
    "done": true
  },
  "securitycraft:recipes/securitycraft/bouncing_betty": {
    "criteria": {
      "has_iron": "2025-10-16 04:09:55 +0000"
    },
    "done": true
  },
  "minecraft:recipes/decorations/stone_brick_wall_from_stone_bricks_stonecutting": {
    "criteria": {
      "has_stone_bricks": "2025-10-16 04:09:55 +0000"
    },
    "done": true
  },
  "farmersdelight:recipes/farmersdelight/mutton_wrap": {
    "criteria": {
      "has_mutton": "2025-10-16 04:04:54 +0000"
    },
    "done": true
  },
  "minecraft:recipes/building_blocks/bricks": {
    "criteria": {
      "has_brick": "2025-10-16 04:04:54 +0000"
    },
    "done": true
  },
  "biomesoplenty:recipes/transportation/redwood_boat": {
    "criteria": {
      "in_water": "2025-10-16 03:52:13 +0000"
    },
    "done": true
  },
  "minecraft:recipes/building_blocks/chiseled_stone_bricks_from_stone_bricks_stonecutting": {
    "criteria": {
      "has_stone_bricks": "2025-10-16 04:09:55 +0000"
    },
    "done": true
  },
  "minecraft:recipes/building_blocks/iron_block": {
    "criteria": {
      "has_iron_ingot": "2025-10-16 04:09:55 +0000"
    },
    "done": true
  },
  "minecraft:recipes/redstone/birch_button": {
    "criteria": {
      "has_planks": "2025-10-16 05:46:58 +0000"
    },
    "done": true
  },
  "blue_skies:recipes/blue_skies_everdawn_blocks/maple_trapdoor": {
    "criteria": {
      "has_item": "2025-10-16 04:01:41 +0000"
    },
    "done": true
  },
  "securitycraft:recipes/securitycraft/sc_manual": {
    "criteria": {
      "has_wood": "2025-10-16 03:49:30 +0000"
    },
    "done": true
  },
  "securitycraft:recipes/securitycraft/keycard_lv4": {
    "criteria": {
      "has_iron": "2025-10-16 04:09:55 +0000"
    },
    "done": true
  },
  "securitycraft:recipes/securitycraft/keycard_lv3": {
    "criteria": {
      "has_iron": "2025-10-16 04:09:55 +0000"
    },
    "done": true
  },
  "securitycraft:recipes/securitycraft/keycard_lv5": {
    "criteria": {
      "has_iron": "2025-10-16 04:09:55 +0000"
    },
    "done": true
  },
  "minecraft:recipes/building_blocks/coal_block": {
    "criteria": {
      "has_coal": "2025-10-16 04:47:25 +0000"
    },
    "done": true
  },
  "mowziesmobs:root": {
    "criteria": {
      "custom_test_name": "2025-10-16 03:48:32 +0000"
    },
    "done": true
  },
  "securitycraft:recipes/securitycraft/reinforced_birch_fence": {
    "criteria": {
      "has_stick": "2025-10-16 03:49:59 +0000"
    },
    "done": true
  },
  "minecraft:story/deflect_arrow": {
    "criteria": {
      "deflected_projectile": "2025-10-16 04:19:18 +0000"
    },
    "done": true
  },
  "minecraft:recipes/redstone/light_weighted_pressure_plate": {
    "criteria": {
      "has_gold_ingot": "2025-10-16 05:51:43 +0000"
    },
    "done": true
  },
  "minecraft:recipes/misc/gold_nugget_from_blasting": {
    "criteria": {
      "has_golden_horse_armor": "2025-10-16 03:55:26 +0000"
    },
    "done": true
  },
  "minecraft:recipes/combat/wooden_sword": {
    "criteria": {
      "has_stick": "2025-10-16 03:49:59 +0000"
    },
    "done": true
  },
  "minecraft:recipes/tools/stone_shovel": {
    "criteria": {
      "has_cobblestone": "2025-10-16 03:50:15 +0000"
    },
    "done": true
  },
  "blue_skies:recipes/blue_skies_everdawn_blocks/maple_pressure_plate": {
    "criteria": {
      "has_item": "2025-10-16 04:01:41 +0000"
    },
    "done": true
  },
  "minecraft:recipes/building_blocks/oak_planks": {
    "criteria": {
      "has_logs": "2025-10-16 03:49:30 +0000"
    },
    "done": true
  },
  "securitycraft:recipes/securitycraft/reinforced_jungle_fence_gate": {
    "criteria": {
      "has_stick": "2025-10-16 03:49:59 +0000"
    },
    "done": true
  },
  "scalinghealth:recipes/scalinghealth/bandages": {
    "criteria": {
      "cobblestone": "2025-10-16 03:50:15 +0000"
    },
    "done": true
  },
  "tombstone:adventure/root": {
    "criteria": {
      "auto": "2025-10-16 03:48:31 +0000"
    },
    "done": true
  },
  "betterendforge:recipes/betterendforge/ender_block": {
    "criteria": {
      "has_ender_pearl": "2025-10-16 04:19:52 +0000"
    },
    "done": true
  },
  "minecraft:recipes/building_blocks/spruce_slab": {
    "criteria": {
      "has_planks": "2025-10-16 04:47:13 +0000"
    },
    "done": true
  },
  "cataclysm:root": {
    "criteria": {
      "custom_test_name": "2025-10-16 03:48:32 +0000"
    },
    "done": true
  },
  "securitycraft:recipes/securitycraft/reinforced_andesite": {
    "criteria": {
      "has_cobblestone": "2025-10-16 03:50:15 +0000"
    },
    "done": true
  },
  "blue_skies:recipes/blue_skies_misc/maple_stick": {
    "criteria": {
      "has_item": "2025-10-16 04:01:41 +0000"
    },
    "done": true
  },
  "securitycraft:recipes/securitycraft/smart_module": {
    "criteria": {
      "has_iron": "2025-10-16 04:09:55 +0000"
    },
    "done": true
  },
  "blue_skies:recipes/blue_skies_everdawn_blocks/maple_slab": {
    "criteria": {
      "has_item": "2025-10-16 04:01:41 +0000"
    },
    "done": true
  },
  "minecraft:recipes/tools/golden_axe": {
    "criteria": {
      "has_gold_ingot": "2025-10-16 05:51:43 +0000"
    },
    "done": true
  },
  "securitycraft:recipes/securitycraft/block_change_detector": {
    "criteria": {
      "has_iron": "2025-10-16 04:09:55 +0000"
    },
    "done": true
  },
  "minecraft:recipes/tools/iron_axe": {
    "criteria": {
      "has_iron_ingot": "2025-10-16 04:09:55 +0000"
    },
    "done": true
  },
  "betterendforge:recipes/betterendforge/terminite_shovel_smithing": {
    "criteria": {
      "has_stick": "2025-10-16 03:49:59 +0000"
    },
    "done": true
  },
  "scalinghealth:recipes/scalinghealth/heart_crystal": {
    "criteria": {
      "cobblestone": "2025-10-16 03:50:15 +0000"
    },
    "done": true
  },
  "securitycraft:recipes/securitycraft/floor_trap": {
    "criteria": {
      "has_iron": "2025-10-16 04:09:55 +0000"
    },
    "done": true
  },
  "minecraft:recipes/combat/golden_helmet": {
    "criteria": {
      "has_gold_ingot": "2025-10-16 05:51:43 +0000"
    },
    "done": true
  },
  "farmersdelight:recipes/farmersdelight/shepherds_pie_block": {
    "criteria": {
      "has_cooked_mutton": "2025-10-16 04:04:54 +0000"
    },
    "done": true
  },
  "minecraft:recipes/redstone/tripwire_hook": {
    "criteria": {
      "has_string": "2025-10-16 04:06:01 +0000"
    },
    "done": true
  },
  "minecraft:recipes/redstone/oak_pressure_plate": {
    "criteria": {
      "has_planks": "2025-10-16 03:49:57 +0000"
    },
    "done": true
  },
  "securitycraft:recipes/securitycraft/reinforced_acacia_fence": {
    "criteria": {
      "has_stick": "2025-10-16 03:49:59 +0000"
    },
    "done": true
  },
  "minecraft:recipes/combat/iron_boots": {
    "criteria": {
      "has_iron_ingot": "2025-10-16 04:09:55 +0000"
    },
    "done": true
  },
  "minecraft:recipes/misc/bone_meal": {
    "criteria": {
      "has_bone": "2025-10-16 03:55:26 +0000"
    },
    "done": true
  },
  "securitycraft:recipes/securitycraft/laser_block": {
    "criteria": {
      "has_stone": "2025-10-16 03:50:15 +0000"
    },
    "done": true
  },
  "endrem:main/rogue_eye": {
    "criteria": {
      "rogue_eye": "2025-10-16 04:05:51 +0000"
    },
    "done": true
  },
  "minecraft:story/iron_tools": {
    "criteria": {
      "iron_pickaxe": "2025-10-16 04:19:52 +0000"
    },
    "done": true
  },
  "blue_skies:recipes/blue_skies_tools/maple_hoe": {
    "criteria": {
      "has_resource": "2025-10-16 04:01:41 +0000"
    },
    "done": true
  },
  "betterendforge:recipes/betterendforge/terminite_axe_smithing": {
    "criteria": {
      "has_stick": "2025-10-16 03:49:59 +0000"
    },
    "done": true
  },
  "farmersdelight:recipes/farmersdelight/iron_knife": {
    "criteria": {
      "has_iron_ingot": "2025-10-16 04:09:55 +0000"
    },
    "done": true
  },
  "minecraft:recipes/building_blocks/oak_wood": {
    "criteria": {
      "has_log": "2025-10-16 03:49:30 +0000"
    },
    "done": true
  },
  "minecraft:recipes/redstone/birch_fence_gate": {
    "criteria": {
      "has_planks": "2025-10-16 05:46:58 +0000"
    },
    "done": true
  },
  "minecraft:story/root": {
    "criteria": {
      "crafting_table": "2025-10-16 03:49:59 +0000"
    },
    "done": true
  },
  "minecraft:recipes/combat/crossbow": {
    "criteria": {
      "has_stick": "2025-10-16 03:49:59 +0000"
    },
    "done": true
  },
  "minecraft:recipes/combat/iron_chestplate": {
    "criteria": {
      "has_iron_ingot": "2025-10-16 04:09:55 +0000"
    },
    "done": true
  },
  "minecraft:recipes/redstone/spruce_pressure_plate": {
    "criteria": {
      "has_planks": "2025-10-16 04:47:13 +0000"
    },
    "done": true
  },
  "minecraft:recipes/redstone/dark_oak_trapdoor": {
    "criteria": {
      "has_planks": "2025-10-16 04:06:01 +0000"
    },
    "done": true
  },
  "minecraft:recipes/decorations/oak_sign": {
    "criteria": {
      "has_oak_planks": "2025-10-16 03:49:57 +0000"
    },
    "done": true
  },
  "shieldexp:recipes/netherite_shield": {
    "criteria": {
      "has_netherite_ingot": "2025-10-16 03:48:31 +0000"
    },
    "done": true
  },
  "minecraft:recipes/redstone/oak_trapdoor": {
    "criteria": {
      "has_planks": "2025-10-16 03:49:57 +0000"
    },
    "done": true
  },
  "scalinghealth:recipes/scalinghealth/heart_dust": {
    "criteria": {
      "cobblestone": "2025-10-16 03:50:15 +0000"
    },
    "done": true
  },
  "minecraft:recipes/misc/iron_nugget_from_blasting": {
    "criteria": {
      "has_chainmail_chestplate": "2025-10-16 04:04:31 +0000"
    },
    "done": true
  },
  "minecraft:recipes/combat/leather_chestplate": {
    "criteria": {
      "has_leather": "2025-10-16 03:52:04 +0000"
    },
    "done": true
  },
  "securitycraft:recipes/securitycraft/reinforced_diorite": {
    "criteria": {
      "has_cobblestone": "2025-10-16 03:50:15 +0000"
    },
    "done": true
  },
  "securitycraft:recipes/securitycraft/trophy_system": {
    "criteria": {
      "has_iron": "2025-10-16 04:09:55 +0000"
    },
    "done": true
  },
  "minecraft:adventure/kill_a_mob": {
    "criteria": {
      "minecraft:skeleton": "2025-10-16 03:54:59 +0000"
    },
    "done": true
  },
  "securitycraft:recipes/securitycraft/camera_monitor": {
    "criteria": {
      "has_iron": "2025-10-16 04:09:55 +0000"
    },
    "done": true
  },
  "minecraft:recipes/redstone/oak_button": {
    "criteria": {
      "has_planks": "2025-10-16 03:49:57 +0000"
    },
    "done": true
  },
  "betterendforge:recipes/betterendforge/thallasium_axe_smithing": {
    "criteria": {
      "has_stick": "2025-10-16 03:49:59 +0000"
    },
    "done": true
  },
  "minecraft:recipes/tools/golden_pickaxe": {
    "criteria": {
      "has_gold_ingot": "2025-10-16 05:51:43 +0000"
    },
    "done": true
  },
  "betterendforge:recipes/betterendforge/thallasium_hoe_smithing": {
    "criteria": {
      "has_stick": "2025-10-16 03:49:59 +0000"
    },
    "done": true
  },
  "securitycraft:recipes/securitycraft/limited_use_keycard": {
    "criteria": {
      "has_iron": "2025-10-16 04:09:55 +0000"
    },
    "done": true
  },
  "farmersdelight:recipes/farmersdelight/flint_knife": {
    "criteria": {
      "has_stick": "2025-10-16 03:49:59 +0000"
    },
    "done": true
  },
  "tombstone:recipes/from_grave_dust": {
    "criteria": {
      "has_ingredient": "2025-10-16 03:55:40 +0000"
    },
    "done": true
  },
  "farmersdelight:recipes/farmersdelight/melon_juice": {
    "criteria": {
      "has_melon_slice": "2025-10-16 04:04:54 +0000"
    },
    "done": true
  },
  "minecraft:recipes/building_blocks/stone": {
    "criteria": {
      "has_cobblestone": "2025-10-16 03:50:15 +0000"
    },
    "done": true
  },
  "minecraft:recipes/redstone/dark_oak_pressure_plate": {
    "criteria": {
      "has_planks": "2025-10-16 04:06:01 +0000"
    },
    "done": true
  },
  "biomesoplenty:recipes/transportation/hellbark_boat": {
    "criteria": {
      "in_water": "2025-10-16 03:52:13 +0000"
    },
    "done": true
  },
  "farmersdelight:recipes/farmersdelight/stuffed_potato": {
    "criteria": {
      "has_baked_potato": "2025-10-16 04:16:05 +0000"
    },
    "done": true
  },
  "minecraft:recipes/food/cooked_beef": {
    "criteria": {
      "has_beef": "2025-10-16 03:52:04 +0000"
    },
    "done": true
  },
  "minecraft:adventure/adventuring_time": {
    "criteria": {
      "minecraft:forest": "2025-10-16 05:54:11 +0000",
      "minecraft:mountains": "2025-10-16 05:21:55 +0000",
      "minecraft:desert_hills": "2025-10-16 05:30:25 +0000",
      "minecraft:desert": "2025-10-16 05:28:05 +0000",
      "minecraft:birch_forest": "2025-10-16 04:28:39 +0000",
      "minecraft:dark_forest": "2025-10-16 04:03:18 +0000",
      "minecraft:river": "2025-10-16 03:51:59 +0000",
      "minecraft:wooded_hills": "2025-10-16 05:54:18 +0000",
      "minecraft:swamp": "2025-10-16 04:35:35 +0000",
      "minecraft:savanna": "2025-10-16 05:46:01 +0000"
    },
    "done": false
  },
  "minecraft:recipes/redstone/iron_door": {
    "criteria": {
      "has_iron_ingot": "2025-10-16 04:09:55 +0000"
    },
    "done": true
  },
  "tombstone:adventure/find_easter_egg": {
    "criteria": {
      "coded_trigger": "2025-10-16 03:48:31 +0000"
    },
    "done": true
  },
  "securitycraft:recipes/securitycraft/whitelist_module": {
    "criteria": {
      "has_iron": "2025-10-16 04:09:55 +0000"
    },
    "done": true
  },
  "vanillahammers:recipes/tools/wood_hammer": {
    "criteria": {
      "has_material": "2025-10-16 03:49:30 +0000"
    },
    "done": true
  },
  "betterendforge:recipes/betterendforge/terminite_hoe_smithing": {
    "criteria": {
      "has_stick": "2025-10-16 03:49:59 +0000"
    },
    "done": true
  },
  "minecraft:recipes/combat/stone_sword": {
    "criteria": {
      "has_cobblestone": "2025-10-16 03:50:15 +0000"
    },
    "done": true
  },
  "dungeons_plus:adventure/find_tower": {
    "criteria": {
      "structure": "2025-10-16 03:54:45 +0000"
    },
    "done": true
  },
  "minecraft:recipes/decorations/barrel": {
    "criteria": {
      "has_planks": "2025-10-16 03:49:57 +0000"
    },
    "done": true
  },
  "securitycraft:recipes/securitycraft/reinforced_warped_fence": {
    "criteria": {
      "has_stick": "2025-10-16 03:49:59 +0000"
    },
    "done": true
  },
  "minecraft:recipes/decorations/cobblestone_wall": {
    "criteria": {
      "has_cobblestone": "2025-10-16 03:50:15 +0000"
    },
    "done": true
  },
  "minecraft:recipes/tools/stone_pickaxe": {
    "criteria": {
      "has_cobblestone": "2025-10-16 03:50:15 +0000"
    },
    "done": true
  },
  "blue_skies:recipes/blue_skies_everdawn_blocks/maple_fence_gate": {
    "criteria": {
      "has_item": "2025-10-16 04:01:41 +0000"
    },
    "done": true
  },
  "minecraft:recipes/decorations/smithing_table": {
    "criteria": {
      "has_iron_ingot": "2025-10-16 04:09:55 +0000"
    },
    "done": true
  },
  "minecraft:recipes/redstone/oak_door": {
    "criteria": {
      "has_planks": "2025-10-16 03:49:57 +0000"
    },
    "done": true
  },
  "securitycraft:recipes/securitycraft/motion_activated_light": {
    "criteria": {
      "has_stick": "2025-10-16 03:49:59 +0000"
    },
    "done": true
  },
  "minecraft:recipes/combat/leather_boots": {
    "criteria": {
      "has_leather": "2025-10-16 03:52:04 +0000"
    },
    "done": true
  },
  "minecraft:recipes/transportation/jungle_boat": {
    "criteria": {
      "in_water": "2025-10-16 03:52:13 +0000"
    },
    "done": true
  },
  "minecraft:recipes/decorations/cobblestone_wall_from_cobblestone_stonecutting": {
    "criteria": {
      "has_cobblestone": "2025-10-16 03:50:15 +0000"
    },
    "done": true
  },
  "minecraft:adventure/shoot_arrow": {
    "criteria": {
      "shot_arrow": "2025-10-16 05:31:49 +0000"
    },
    "done": true
  },
  "blue_skies:recipes/blue_skies_everdawn_blocks/maple_door": {
    "criteria": {
      "has_item": "2025-10-16 04:01:41 +0000"
    },
    "done": true
  },
  "securitycraft:recipes/securitycraft/mine": {
    "criteria": {
      "has_iron": "2025-10-16 04:09:55 +0000"
    },
    "done": true
  },
  "minecraft:recipes/building_blocks/birch_stairs": {
    "criteria": {
      "has_planks": "2025-10-16 05:46:58 +0000"
    },
    "done": true
  },
  "minecraft:recipes/redstone/heavy_weighted_pressure_plate": {
    "criteria": {
      "has_iron_ingot": "2025-10-16 04:09:55 +0000"
    },
    "done": true
  },
  "iceandfire:iceandfire/kill_ghost": {
    "criteria": {
      "killed_fire_dragon": "2025-10-16 05:31:40 +0000"
    },
    "done": true
  },
  "farmersdelight:recipes/farmersdelight/golden_knife": {
    "criteria": {
      "has_gold_ingot": "2025-10-16 05:51:43 +0000"
    },
    "done": true
  },
  "minecraft:recipes/transportation/dark_oak_boat": {
    "criteria": {
      "in_water": "2025-10-16 03:52:13 +0000"
    },
    "done": true
  },
  "minecraft:recipes/transportation/carrot_on_a_stick": {
    "criteria": {
      "has_carrot": "2025-10-16 04:06:21 +0000"
    },
    "done": true
  },
  "minecraft:recipes/decorations/flower_pot": {
    "criteria": {
      "has_brick": "2025-10-16 04:04:54 +0000"
    },
    "done": true
  },
  "dungeons_arise:wda_root": {
    "criteria": {
      "WDA": "2025-10-16 03:48:32 +0000"
    },
    "done": true
  },
  "blue_skies:recipes/blue_skies_everdawn_blocks/maple_crafting_table": {
    "criteria": {
      "has_item": "2025-10-16 04:01:41 +0000"
    },
    "done": true
  },
  "securitycraft:recipes/securitycraft/universal_owner_changer": {
    "criteria": {
      "has_name_tag": "2025-10-16 04:07:13 +0000"
    },
    "done": true
  },
  "blue_skies:recipes/blue_skies_everdawn_blocks/maple_sign": {
    "criteria": {
      "has_item": "2025-10-16 04:01:41 +0000"
    },
    "done": true
  },
  "minecraft:recipes/redstone/birch_trapdoor": {
    "criteria": {
      "has_planks": "2025-10-16 05:46:58 +0000"
    },
    "done": true
  },
  "securitycraft:recipes/securitycraft/briefcase": {
    "criteria": {
      "has_iron": "2025-10-16 04:09:55 +0000"
    },
    "done": true
  },
  "minecraft:recipes/combat/golden_leggings": {
    "criteria": {
      "has_gold_ingot": "2025-10-16 05:51:43 +0000"
    },
    "done": true
  },
  "minecraft:recipes/decorations/lantern": {
    "criteria": {
      "has_iron_ingot": "2025-10-16 04:09:55 +0000"
    },
    "done": true
  },
  "securitycraft:recipes/securitycraft/reinforced_oak_fence_gate": {
    "criteria": {
      "has_stick": "2025-10-16 03:49:59 +0000"
    },
    "done": true
  },
  "biomesoplenty:recipes/transportation/jacaranda_boat": {
    "criteria": {
      "in_water": "2025-10-16 03:52:13 +0000"
    },
    "done": true
  },
  "endrem:main/root": {
    "criteria": {
      "rogue_eye": "2025-10-16 04:05:51 +0000"
    },
    "done": true
  },
  "minecraft:recipes/redstone/spruce_trapdoor": {
    "criteria": {
      "has_planks": "2025-10-16 04:47:13 +0000"
    },
    "done": true
  },
  "farmersdelight:recipes/farmersdelight/barbecue_stick": {
    "criteria": {
      "has_cooked_beef": "2025-10-16 04:02:16 +0000"
    },
    "done": true
  },
  "minecraft:recipes/food/cooked_beef_from_campfire_cooking": {
    "criteria": {
      "has_beef": "2025-10-16 03:52:04 +0000"
    },
    "done": true
  },
  "minecraft:recipes/misc/gold_nugget_from_smelting": {
    "criteria": {
      "has_golden_horse_armor": "2025-10-16 03:55:26 +0000"
    },
    "done": true
  },
  "minecraft:recipes/decorations/dark_oak_fence": {
    "criteria": {
      "has_planks": "2025-10-16 04:06:01 +0000"
    },
    "done": true
  },
  "securitycraft:recipes/securitycraft/reinforced_fence_gate": {
    "criteria": {
      "has_iron": "2025-10-16 04:09:55 +0000"
    },
    "done": true
  },
  "shieldexp:recipes/golden_shield": {
    "criteria": {
      "has_gold_ingot": "2025-10-16 03:48:31 +0000"
    },
    "done": true
  },
  "voidtotem:recipes/combat/totem_of_void_undying": {
    "criteria": {
      "has_emerald": "2025-10-16 04:24:12 +0000"
    },
    "done": true
  },
  "minecraft:recipes/decorations/soul_campfire": {
    "criteria": {
      "has_stick": "2025-10-16 03:49:59 +0000"
    },
    "done": true
  },
  "minecraft:story/smelt_iron": {
    "criteria": {
      "iron": "2025-10-16 04:09:55 +0000"
    },
    "done": true
  },
  "minecraft:recipes/tools/stone_axe": {
    "criteria": {
      "has_cobblestone": "2025-10-16 03:50:15 +0000"
    },
    "done": true
  },
  "minecraft:recipes/building_blocks/melon": {
    "criteria": {
      "has_melon": "2025-10-16 04:04:54 +0000"
    },
    "done": true
  },
  "morevillagers:first_workstation_get": {
    "criteria": {
      "barrel": "2025-10-16 03:53:16 +0000"
    },
    "done": true
  },
  "securitycraft:recipes/securitycraft/disguise_module": {
    "criteria": {
      "has_iron": "2025-10-16 04:09:55 +0000"
    },
    "done": true
  },
  "betterendforge:recipes/betterendforge/infusion_pedestal": {
    "criteria": {
      "has_ender_pearl": "2025-10-16 04:19:52 +0000"
    },
    "done": true
  },
  "securitycraft:recipes/securitycraft/reinforced_dark_oak_fence": {
    "criteria": {
      "has_stick": "2025-10-16 03:49:59 +0000"
    },
    "done": true
  },
  "repurposed_structures:root": {
    "criteria": {
      "always": "2025-10-16 03:48:32 +0000"
    },
    "done": true
  },
  "tombstone:adventure/ambush": {
    "criteria": {
      "coded_trigger": "2025-10-16 04:47:43 +0000"
    },
    "done": true
  },
  "DataVersion": 2586
}